Metadata-Version: 2.1
Name: one-readme
Version: 0.3
Summary: Only CLI Package you need to manage all your Readme.
Home-page: https://github.com/sarvesh4396/Readme
Author: Sarvesh Kumar Dwivedi
License: UNKNOWN
Download-URL: https://github.com/sarvesh4396/Readme/archive/refs/tags/v0.3.tar.gz
Keywords: one_readme,one_readme,Github
Platform: UNKNOWN
Classifier: Development Status :: 3 - Alpha
Classifier: Topic :: Internet
Classifier: Topic :: Utilities
Classifier: Topic :: Software Development :: Build Tools
Classifier: Topic :: Software Development :: Version Control :: Git
Classifier: Environment :: Console
Classifier: Topic :: Communications :: File Sharing
Classifier: Natural Language :: English
Classifier: Operating System :: OS Independent
Classifier: License :: OSI Approved :: BSD License
Classifier: Programming Language :: Python
Classifier: Programming Language :: Python :: 3 :: Only
Classifier: Programming Language :: Python :: 3
Classifier: Programming Language :: Python :: 3.7
Classifier: Programming Language :: Python :: 3.8
Classifier: Programming Language :: Python :: Implementation :: PyPy
Requires-Python: >=3.7.0
